iflow_mcp_yusufkaraaslan_skill_seekers-2.5.2.dist-info/licenses/LICENSE
skill_seekers/__init__.py
skill_seekers/py.typed
skill_seekers/cli/__init__.py
skill_seekers/cli/api_reference_builder.py
skill_seekers/cli/code_analyzer.py
skill_seekers/cli/codebase_scraper.py
skill_seekers/cli/config_validator.py
skill_seekers/cli/conflict_detector.py
skill_seekers/cli/constants.py
skill_seekers/cli/dependency_analyzer.py
skill_seekers/cli/doc_scraper.py
skill_seekers/cli/enhance_skill.py
skill_seekers/cli/enhance_skill_local.py
skill_seekers/cli/estimate_pages.py
skill_seekers/cli/generate_router.py
skill_seekers/cli/github_scraper.py
skill_seekers/cli/install_agent.py
skill_seekers/cli/install_skill.py
skill_seekers/cli/language_detector.py
skill_seekers/cli/llms_txt_detector.py
skill_seekers/cli/llms_txt_downloader.py
skill_seekers/cli/llms_txt_parser.py
skill_seekers/cli/main.py
skill_seekers/cli/merge_sources.py
skill_seekers/cli/package_multi.py
skill_seekers/cli/package_skill.py
skill_seekers/cli/pattern_recognizer.py
skill_seekers/cli/pdf_extractor_poc.py
skill_seekers/cli/pdf_scraper.py
skill_seekers/cli/quality_checker.py
skill_seekers/cli/run_tests.py
skill_seekers/cli/split_config.py
skill_seekers/cli/swift_patterns.py
skill_seekers/cli/test_unified_simple.py
skill_seekers/cli/unified_scraper.py
skill_seekers/cli/unified_skill_builder.py
skill_seekers/cli/upload_skill.py
skill_seekers/cli/utils.py
skill_seekers/cli/adaptors/__init__.py
skill_seekers/cli/adaptors/base.py
skill_seekers/cli/adaptors/claude.py
skill_seekers/cli/adaptors/gemini.py
skill_seekers/cli/adaptors/markdown.py
skill_seekers/cli/adaptors/openai.py
skill_seekers/mcp/__init__.py
skill_seekers/mcp/agent_detector.py
skill_seekers/mcp/git_repo.py
skill_seekers/mcp/server.py
skill_seekers/mcp/server_fastmcp.py
skill_seekers/mcp/server_legacy.py
skill_seekers/mcp/source_manager.py
skill_seekers/mcp/tools/__init__.py
skill_seekers/mcp/tools/config_tools.py
skill_seekers/mcp/tools/packaging_tools.py
skill_seekers/mcp/tools/scraping_tools.py
iflow_mcp_yusufkaraaslan_skill_seekers-2.5.2.dist-info/METADATA
iflow_mcp_yusufkaraaslan_skill_seekers-2.5.2.dist-info/WHEEL
iflow_mcp_yusufkaraaslan_skill_seekers-2.5.2.dist-info/entry_points.txt
iflow_mcp_yusufkaraaslan_skill_seekers-2.5.2.dist-info/top_level.txt
iflow_mcp_yusufkaraaslan_skill_seekers-2.5.2.dist-info/RECORD
